cognite/client/__init__.py
cognite/client/_api_client.py
cognite/client/_cognite_client.py
cognite/client/_http_client.py
cognite/client/_version.py
cognite/client/beta.py
cognite/client/exceptions.py
cognite/client/experimental.py
cognite/client/testing.py
cognite/client/_api/__init__.py
cognite/client/_api/annotations.py
cognite/client/_api/assets.py
cognite/client/_api/data_sets.py
cognite/client/_api/datapoints.py
cognite/client/_api/diagrams.py
cognite/client/_api/entity_matching.py
cognite/client/_api/events.py
cognite/client/_api/extractionpipelines.py
cognite/client/_api/files.py
cognite/client/_api/geospatial.py
cognite/client/_api/iam.py
cognite/client/_api/labels.py
cognite/client/_api/login.py
cognite/client/_api/raw.py
cognite/client/_api/relationships.py
cognite/client/_api/sequences.py
cognite/client/_api/synthetic_time_series.py
cognite/client/_api/templates.py
cognite/client/_api/three_d.py
cognite/client/_api/time_series.py
cognite/client/_api/transformations/__init__.py
cognite/client/_api/transformations/jobs.py
cognite/client/_api/transformations/notifications.py
cognite/client/_api/transformations/schedules.py
cognite/client/_api/transformations/schema.py
cognite/client/data_classes/__init__.py
cognite/client/data_classes/_base.py
cognite/client/data_classes/annotations.py
cognite/client/data_classes/assets.py
cognite/client/data_classes/contextualization.py
cognite/client/data_classes/data_sets.py
cognite/client/data_classes/datapoints.py
cognite/client/data_classes/events.py
cognite/client/data_classes/extractionpipelines.py
cognite/client/data_classes/files.py
cognite/client/data_classes/geospatial.py
cognite/client/data_classes/iam.py
cognite/client/data_classes/labels.py
cognite/client/data_classes/login.py
cognite/client/data_classes/raw.py
cognite/client/data_classes/relationships.py
cognite/client/data_classes/sequences.py
cognite/client/data_classes/shared.py
cognite/client/data_classes/templates.py
cognite_sdk_core-2.56.1.dist-info/LICENSE
cognite_sdk_core-2.56.1.dist-info/METADATA
cognite_sdk_core-2.56.1.dist-info/WHEEL
cognite_sdk_core-2.56.1.dist-info/top_level.txt
cognite_sdk_core-2.56.1.dist-info/RECORD
