Metadata-Version: 2.1
Name: cognite-sdk-core
Version: 2.56.1
Summary: Client library for Cognite Data Fusion (CDF)
Home-page: https://cognite-sdk-python.readthedocs-hosted.com
Download-URL: https://github.com/cognitedata/cognite-sdk-python/archive/2.56.1.tar.gz
Author: Erlend Vollset
Author-email: erlend.vollset@cognite.com
License: UNKNOWN
Platform: UNKNOWN
Requires-Python: >=3.5
License-File: LICENSE
Requires-Dist: requests (<3.0.0,>=2.21.0)
Requires-Dist: requests-oauthlib (==1.3.0)
Provides-Extra: geo
Requires-Dist: geopandas (==0.10.*) ; extra == 'geo'
Requires-Dist: shapely (==1.*) ; extra == 'geo'
Provides-Extra: pandas
Requires-Dist: pandas ; extra == 'pandas'
